eim/__init__.py
eim/documents/__init__.py
eim/tools/__init__.py
eim/tools/analysis.py
eim/tools/database.py
eim/tools/document.py
eim-0.2.6.dist-info/METADATA
eim-0.2.6.dist-info/RECORD
eim-0.2.6.dist-info/WHEEL
eim-0.2.6.dist-info/top_level.txt
