Metadata-Version: 2.1
Name: eim
Version: 0.2.6
Summary: Library for interacting with Emotion and Motion resources
Home-page: http://www.musicsensorsemotion.com/
Author: Brennon Bortz
Author-email: brennon@vt.edu
License: UNKNOWN
Platform: UNKNOWN
Requires-Dist: pymongo
Requires-Dist: pandas
Requires-Dist: mongoengine (>=0.10.6)
Requires-Dist: numpy
Requires-Dist: scipy
